{"usuarios":{"1":{"nome":"Renan Bertoldo1","email":"renan8r@gmail.com","dt_nascimento":"10\/12\/1995","senha":"1234"},"4":{"nome":"Renan 2","email":"renan2@.c","dt_nascimento":"11\/11\/1212","senha":"123"},"5":{"nome":"Afdsf","email":"fdsfsd","dt_nascimento":"2131","senha":"123"},"6":{"nome":"dsfdsfsd","email":"fdsfsd","dt_nascimento":"dsff","senha":"sdf"},"7":{"nome":"Renan Rafael Bertoldo","email":"renan10r_@hotmail.com","dt_nascimento":"10\/12\/1995","senha":"123","imoveis":[{"nome":"fdsfds1","suites":"32","quartos":"23","area_privativa":"32","area_total":"32","vaga_garagem":"4","cep":"432432","estado":"fsdf","cidade":"fdsf","bairro":"fds","rua":"fdsf","numero":"43","caracteristicas":"sdfsdf","informacoes_adicionais":"sdfds"}]}}}